sentry_webhook/__init__.py
sentry_webhook/plugin.py
sentry_alert_webhook-1.0.1.dist-info/METADATA
sentry_alert_webhook-1.0.1.dist-info/WHEEL
sentry_alert_webhook-1.0.1.dist-info/entry_points.txt
sentry_alert_webhook-1.0.1.dist-info/top_level.txt
sentry_alert_webhook-1.0.1.dist-info/RECORD
