Metadata-Version: 2.1
Name: sentry-alert-webhook
Version: 1.0.1
Summary: A Sentry extension which integrates with Dingtalk robot.
Home-page: https://github.com/GaoYuJian/sentry-dingtalk
Author: GaoYuJian
Author-email: gaoyujian2015@gmail.com
License: BSD
Keywords: sentry dingding dingtalk
Platform: any
Classifier: Framework :: Django
Classifier: Intended Audience :: Developers
Classifier: Intended Audience :: System Administrators
Classifier: Operating System :: OS Independent
Classifier: Topic :: Software Development
Requires-Dist: sentry (>=10.0.0)
Provides-Extra: test
